tryhackme/__init__.py
tryhackme/badge.py
tryhackme/checks.py
tryhackme/client.py
tryhackme/cog.py
tryhackme/converters.py
tryhackme/errors.py
tryhackme/http.py
tryhackme/message.py
tryhackme/module.py
tryhackme/network.py
tryhackme/notifications.py
tryhackme/path.py
tryhackme/question.py
tryhackme/room.py
tryhackme/serie.py
tryhackme/state.py
tryhackme/task.py
tryhackme/team.py
tryhackme/user.py
tryhackme/utils.py
tryhackme/vpn.py
tryhackme.py-1.2.1.dist-info/LICENSE
tryhackme.py-1.2.1.dist-info/METADATA
tryhackme.py-1.2.1.dist-info/WHEEL
tryhackme.py-1.2.1.dist-info/top_level.txt
tryhackme.py-1.2.1.dist-info/RECORD
