Metadata-Version: 2.1
Name: tryhackme.py
Version: 1.2.1
Summary: THM public API wrapper
Home-page: https://github.com/gnarlito/tryhackme.py
Author: gnarlito
Author-email: gnarlito35@gmail.com
License: UNKNOWN
Platform: UNKNOWN
Classifier: Programming Language :: Python :: 3
Classifier: License :: OSI Approved :: MIT License
Classifier: Operating System :: OS Independent
Classifier: Development Status :: 4 - Beta
Classifier: Topic :: Internet :: WWW/HTTP
Requires-Python: >=3.8
License-File: LICENSE
Requires-Dist: requests (==2.26.0)
